ucefcuploader/__init__.py
ucefcuploader/core.py
ucefcuploader/utils.py
ucefcuploader/__metadata__/DISCLIAIMER.md
ucefcuploader/__metadata__/LICENSE
ucefcuploader/__metadata__/README.md
ucefcuploader/__metadata__/__init__.py
ucefcuploader/__metadata__/requirements.txt
ucefcuploader-1.5.0.dist-info/METADATA
ucefcuploader-1.5.0.dist-info/WHEEL
ucefcuploader-1.5.0.dist-info/top_level.txt
ucefcuploader-1.5.0.dist-info/RECORD
